
{
  "$schema": "https://developer.microsoft.com/json-schemas/rush/v5/rush.schema.json",
  "rushVersion": "5.42.3",
  "pnpmVersion": "5.15.2",
  "projectFolderMaxDepth": 3,
  "ensureConsistentVersions": true,
  "pnpmOptions": {

  },
  "nodeSupportedVersionRange": ">=12.13.0 <13.0.0 || >=14.15.0 <15.0.0",
  "gitPolicy": {

  },
  "repository": {

  },
  "eventHooks": {
    "preRushInstall": [

    ],
    "postRushInstall": [],
    "preRushBuild": [],
    "postRushBuild": []
  },
  "variants": [

  ],
  "projects": [
    {
      "packageName": "api-server",
      "projectFolder": "servers/api-server"
    },
    {
      "packageName": "notification-server",
      "projectFolder": "servers/notification-server"
    },

    {
      "packageName": "music-player-client",
      "projectFolder": "clients/music-player-client"
    },

    {
      "packageName": "database-pkg",
      "projectFolder": "packages/technical/database-pkg"
    },
    {
      "packageName": "hash-pkg",
      "projectFolder": "packages/technical/hash-pkg"
    },
    {
      "packageName": "env-pkg",
      "projectFolder": "packages/technical/env-pkg"
    },
    {
      "packageName": "utils-pkg",
      "projectFolder": "packages/technical/utils-pkg"
    },
    {
      "packageName": "types-pkg",
      "projectFolder": "packages/technical/types-pkg"
    },
    {
      "packageName": "error-pkg",
      "projectFolder": "packages/technical/error-pkg"
    },
    {
      "packageName": "mq-pkg",
      "projectFolder": "packages/technical/mq-pkg"
    },
    {
      "packageName": "ffmpeg-pkg",
      "projectFolder": "packages/technical/ffmpeg-pkg"
    },
    {
      "packageName": "hub-publish-pkg",
      "projectFolder": "packages/technical/hub-publish-pkg"
    },
    {
      "packageName": "music-metadata-pkg",
      "projectFolder": "packages/technical/music-metadata-pkg"
    },
    {
      "packageName": "filesystem-pkg",
      "projectFolder": "packages/technical/filesystem-pkg"
    },

    {
      "packageName": "validation-pkg",
      "projectFolder": "packages/business/validation-pkg"
    },
    {
      "packageName": "user-pkg",
      "projectFolder": "packages/business/user-pkg"
    },
    {
      "packageName": "playlist-pkg",
      "projectFolder": "packages/business/playlist-pkg"
    },
    {
      "packageName": "music-pkg",
      "projectFolder": "packages/business/music-pkg"
    },
    {
      "packageName": "youtube-pkg",
      "projectFolder": "packages/business/youtube-pkg"
    },
    {
      "packageName": "spotify-pkg",
      "projectFolder": "packages/business/spotify-pkg"
    },
    {
      "packageName": "notification-pkg",
      "projectFolder": "packages/business/notification-pkg"
    },
    {
      "packageName": "downloader-pkg",
      "projectFolder": "packages/business/downloader-pkg"
    }
  ]
}
